{
    "team names": "TEAM GEAR",
    "series number": 201,
    "filename": "ahmed-the-merchant",
    "name": "ahmed the merchant",
    "description": "A rich merchant that sells in babylon.",
    "gender": "Male",
    "attributes": {
        "hair": null,
        "eyes": "closed",
        "teeth": null,
        "clothing": "one-hand",
        "accessories": null,
        "expression": "smiling",
        "strength": "business",
        "weakness": "alcohol"
    },
    "uuid": "9996ecb6-4d92-4b51-bc50-d962f68f1ecc",
    "hash": "d3c513f8b89280a010748718c24dd3a3460cb0289538d3a92ef8849f1829f86d",
    "format": "CHIP-0007",
    "sensitive_content": false
}