{
    "team names": "",
    "series number": 269,
    "filename": "mariam-beauty-queen",
    "name": "mariam beauty queen",
    "description": "Beauty is a fairy tale where mariam appears.",
    "gender": "Female",
    "attributes": {
        "hair": "orange",
        "eyes": "grey",
        "teeth": null,
        "clothing": "multicolour yellow kente",
        "accessories": null,
        "expression": "straight face",
        "strength": "disciplined",
        "weakness": "inability to delegate"
    },
    "uuid": "b7d96d97-84c2-485f-b60e-e4e86c4d3b34",
    "hash": "fa823ded3d3c5b175bf08158724a12dc294e94802ce12e5f646ec5c721d0fa9c",
    "format": "CHIP-0007",
    "sensitive_content": false
}