{
    "team names": "",
    "series number": 213,
    "filename": "musa-masked-mouth",
    "name": "musa masked mouth",
    "description": "Musa uses a tape to cover his mouth to prevent him from talking too much.",
    "gender": "Male",
    "attributes": {
        "hair": "cap",
        "eyes": "closed",
        "teeth": null,
        "clothing": "shirt",
        "accessories": "fashion",
        "expression": null,
        "strength": "dressing",
        "weakness": null
    },
    "uuid": "9a5e7e95-6552-4a92-ab18-2154678943c2",
    "hash": "a595ef64e432e4a2bb83480b8e66aee718fe5abeb7ad69b597f95270b8e7d7b0",
    "format": "CHIP-0007",
    "sensitive_content": false
}